Workbook

Sheet Overview
A1: Zurvival Reborn — Scope-Control Tracker
A2: The living operational layer of PRODUCTION.md. Solo + AI · effort-based · the "no machine".
A5: HOW TO USE THIS BOOK
A6: Milestones | B6: M0–M5 ladder + post-launch. % complete auto-computes from the Backlog. Theme, gate, and risk-retired per milestone.
A7: Backlog | B7: Every PRD requirement as a work item, mapped to milestone, MoSCoW, the principle it serves, effort, and AI-assist. This is the work.
A8: Content Budget | B8: Caps per milestone that protect REVIEW CAPACITY. Set "Current milestone"; a red Headroom cell = stop authoring, go playtest.
A9: Risk Burn-down | B9: Each PRD risk mapped to the milestone that retires it. Update status as you go.
A10: Decision Gates | B10: Open ADRs, each tied to the milestone it must be resolved by. ADR-0001 is the one to force at M0.
A11: Parking Lot | B11: New ideas land here — never in a live milestone. Triage only at boundaries. Pre-seeded with the frozen Won’t-now register.
A12: Fun-Gate Log | B12: Every gate verdict: build, date, the retellable moment, go/no-go. The gate is the point.
A14: THE CUT FILTER — the "no machine"
A15: The rule | B15: A feature must serve ≥ 1 of the six principles. If it serves none, it WAITS or DIES. If it serves one but costs more review capacity than the milestone budget allows, it DEFERS.
A16: P1 | B16: A systemic core loop
A17: P2 | B17: Injuries are stories
A18: P3 | B18: Nodes with memory
A19: P4 | B19: The Survival Triangle (Safety · Resources · Time)
A20: P5 | B20: Handcrafted social simulation
A21: P6 | B21: Artifacts over XP
A23: LEGEND
A24: MoSCoW | B24: Must = milestone not done without it (never cut to hit a date) · Should = cut first · Could = only if ahead · Won’t = frozen
A25: Cut order under pressure | B25: Coulds → Shoulds → re-scope the milestone. NEVER cut a Must or skip a fun gate.
A26: Status colours | B26: Done = green · In progress = amber · Blocked = red · Not started = grey · Cut = struck through
A27: Effort bands | B27: XS <½ wk · S ~1 wk · M ~2–3 wk · L ~4–6 wk · XL ~8+ wk (solo + AI; re-calibrate after M1). >25% over band = scope-review tripwire.

Sheet Milestones
A1: Milestone Ladder
A2: Numbering follows the PRD (M1–M5) + explicit M0 Foundation. % auto-computes from Backlog status.
A4: ID | B4: Milestone | C4: Theme | D4: Horizon | E4: Effort | F4: % done | G4: Fun gate | H4: Risk retired | I4: Definition of done (short)
A5: M0 | B5: Foundation | C5: The skeleton runs | D5: pre-VS | E5: M | F5: =IFERROR(COUNTIFS(Backlog!$D:$D,$A5,Backlog!$J:$J,"Done")/COUNTIFS(Backlog!$D:$D,$A5),"—") -> 0 | G5: — | H5: Undecided stack / paralysis | I5: Deterministic core runs the full pipeline; save round-trips; CI rejects malformed content.
A6: M1 | B6: Core loop playable | C6: The loop is satisfying | D6: Vertical Slice | E6: L | F6: =IFERROR(COUNTIFS(Backlog!$D:$D,$A6,Backlog!$J:$J,"Done")/COUNTIFS(Backlog!$D:$D,$A6),"—") -> 0 | G6: Loop-Feel Check | H6: (loop-feel read) | I6: A slice of turns runs end-to-end; every turn changes ≥1 system; stealth path exists; lossless resume.
A7: M2 | B7: Reactive world | C7: The world moves on its own | D7: Vertical Slice | E7: L | F7: =IFERROR(COUNTIFS(Backlog!$D:$D,$A7,Backlog!$J:$J,"Done")/COUNTIFS(Backlog!$D:$D,$A7),"—") -> 0 | G7: — | H7: Impressive but static | I7: Region threat shifts off-screen; gunshot re-paths a horde; director biases without breaking logic.
A8: M3 | B8: People, shelter & first story | C8: A run becomes a story | D8: Vertical Slice — complete | E8: XL | F8: =IFERROR(COUNTIFS(Backlog!$D:$D,$A8,Backlog!$J:$J,"Done")/COUNTIFS(Backlog!$D:$D,$A8),"—") -> 0 | G8: SLICE FUN GATE (decisive) | H8: Systemic but not fun | I8: A full slice run yields an emergent, retellable story; companion fate lands; shelter loss is survivable.
A9: M4 | B9: Content-complete city | C9: Breadth without repetition | D9: MVP / public beta | E9: XL | F9: =IFERROR(COUNTIFS(Backlog!$D:$D,$A9,Backlog!$J:$J,"Done")/COUNTIFS(Backlog!$D:$D,$A9),"—") -> 0 | G9: — | H9: Content volume | I9: One city content-complete & schema-valid; repeat-rate under target; infection-as-identity comprehensible.
A10: M5 | B10: Release candidate | C10: Balanced, accessible, hardened | D10: v1.0 launch | E10: XL | F10: =IFERROR(COUNTIFS(Backlog!$D:$D,$A10,Backlog!$J:$J,"Done")/COUNTIFS(Backlog!$D:$D,$A10),"—") -> 0 | G10: "one more day" w/ externals | H10: Balance fragility · save churn | I10: Every Must met; balance targets hit; save survives migration; accessibility verified with assistive tech.
A11: P+ | B11: Post-launch | C11: Content cadence + new clients | D11: live | E11: ongoing | F11: =IFERROR(COUNTIFS(Backlog!$D:$D,$A11,Backlog!$J:$J,"Done")/COUNTIFS(Backlog!$D:$D,$A11),"—") -> — | G11: — | H11: Long-tail relevance | I11: Expansion-hook content needing no engine rewrite; then native & chat-bot clients (ADR-0004).
A13: Gate rule: if the Slice Fun Gate (M3) fails, scope re-invests in the loop/characters — content stays frozen. Never "add content" to fix fun.

Sheet Backlog
A1: Backlog
A2: Every PRD requirement as a work item. Traces to the PRD by ID. Filter by Milestone / MoSCoW / Status.
A4: ID | B4: Area | C4: Requirement | D4: Milestone | E4: MoSCoW | F4: Type | G4: Serves | H4: Effort | I4: AI-assist | J4: Status | K4: DoD met | L4: Notes
A5: PROD-01 | B5: Foundation | C5: ADR-0001: choose engine language & runtime (time-boxed) | D5: M0 | E5: Must | F5: Decision | G5: P1 | H5: S | I5: No | J5: Not started | K5: No
A6: PROD-02 | B6: Foundation | C6: GameState shape + turn-pipeline shell (14 stages) | D6: M0 | E6: Must | F6: Engine | G6: P1 | H6: M | I6: Yes | J6: Not started | K6: No
A7: PROD-03 | B7: Foundation | C7: Seeded RNG with named streams, serialized with state | D7: M0 | E7: Must | F7: Engine | G7: P1 | H7: S | I7: Yes | J7: Not started | K7: No
A8: PROD-04 | B8: Foundation | C8: Content loader + first schemas | D8: M0 | E8: Must | F8: Engine | G8: P1 | H8: M | I8: Yes | J8: Not started | K8: No
A9: PROD-05 | B9: Foundation | C9: CI: malformed content fails the build | D9: M0 | E9: Must | F9: Infra | G9: P1 | H9: S | I9: Yes | J9: Not started | K9: No
A10: PROD-06 | B10: Foundation | C10: Determinism / golden-run test harness | D10: M0 | E10: Must | F10: QA | G10: P1 | H10: M | I10: Yes | J10: Not started | K10: No
A11: PROD-07 | B11: Foundation | C11: Terminal harness runs an empty turn | D11: M0 | E11: Must | F11: Client | G11: P1 | H11: S | I11: Yes | J11: Not started | K11: No
A12: FR-CNT-01 | B12: Content pipeline | C12: Content authored as external data, loaded at runtime | D12: M0 | E12: Must | F12: Engine | G12: P1 | H12: M | I12: Yes | J12: Not started | K12: No
A13: FR-CNT-02 | B13: Content pipeline | C13: Content validated vs schemas in CI | D13: M0 | E13: Must | F13: Infra | G13: P1 | H13: S | I13: Yes | J13: Not started | K13: No
A14: NFR-PLAT-02 | B14: Platform | C14: Headless / renderer-agnostic engine | D14: M0 | E14: Must | F14: Engine | G14: P1 | H14: M | I14: Yes | J14: Not started | K14: No
A15: FR-CORE-01 | B15: Core loop | C15: Turn loop, no direct choice→scene edge | D15: M1 | E15: Must | F15: Engine | G15: P1 | H15: M | I15: Yes | J15: Not started | K15: No
A16: FR-CORE-02 | B16: Core loop | C16: Fixed pipeline order executed every turn | D16: M1 | E16: Must | F16: Engine | G16: P1 | H16: S | I16: Yes | J16: Not started | K16: No
... A156: PROD-12 | B156: Saves | C156: Save migration proven across a schema change | D156: M5 | E156: Must | F156: QA | G156: P1 | H156: M | I156: Yes | J156: Not started | K156: No

Sheet Content Budget
A1: Content Budget
A2: Caps that protect REVIEW CAPACITY. Set the current milestone; a red Headroom = stop authoring, go playtest.
A4: Current milestone: | B4: M1 | D4: ← change this; caps & headroom update automatically
A6: Content type | B6: Cap (this milestone) | C6: Actual (update) | D6: Headroom | E6: Status | H6: type | I6: M1 | J6: M2 | K6: M3 | L6: M4 | M6: M5
A7: Regions | B7: =INDEX($I7:$M7,MATCH($B$4,$I$6:$M$6,0)) -> 1 | C7: 0 | D7: =B7-C7 -> 1 | E7: =IF(B7=0,IF(C7>0,"OVER — cut","none this milestone"),IF(D7<0,"OVER — stop & playtest",IF(D7=0,"AT CAP",D7&" left"))) -> 1 left | H7: Regions | I7: 1 | J7: 1 | K7: 1 | L7: 6 | M7: 6
A8: Nodes | B8: =INDEX($I8:$M8,MATCH($B$4,$I$6:$M$6,0)) -> 8 | C8: 0 | D8: =B8-C8 -> 8 | E8: =IF(B8=0,IF(C8>0,"OVER — cut","none this milestone"),IF(D8<0,"OVER — stop & playtest",IF(D8=0,"AT CAP",D8&" left"))) -> 8 left | H8: Nodes | I8: 8 | J8: 8 | K8: 8 | L8: 60 | M8: 60
A9: Survivors | B9: =INDEX($I9:$M9,MATCH($B$4,$I$6:$M$6,0)) -> 1 | C9: 0 | D9: =B9-C9 -> 1 | E9: =IF(B9=0,IF(C9>0,"OVER — cut","none this milestone"),IF(D9<0,"OVER — stop & playtest",IF(D9=0,"AT CAP",D9&" left"))) -> 1 left | H9: Survivors | I9: 1 | J9: 1 | K9: 5 | L9: 100 | M9: 100
A10: Companions | B10: =INDEX($I10:$M10,MATCH($B$4,$I$6:$M$6,0)) -> 0 | C10: 0 | D10: =B10-C10 -> 0 | E10: =IF(B10=0,IF(C10>0,"OVER — cut","none this milestone"),IF(D10<0,"OVER — stop & playtest",IF(D10=0,"AT CAP",D10&" left"))) -> none this milestone | H10: Companions | I10: 0 | J10: 0 | K10: 1 | L10: 6 | M10: 6
A11: Zombie types | B11: =INDEX($I11:$M11,MATCH($B$4,$I$6:$M$6,0)) -> 2 | C11: 0 | D11: =B11-C11 -> 2 | E11: =IF(B11=0,IF(C11>0,"OVER — cut","none this milestone"),IF(D11<0,"OVER — stop & playtest",IF(D11=0,"AT CAP",D11&" left"))) -> 2 left | H11: Zombie types | I11: 2 | J11: 4 | K11: 4 | L11: 8 | M11: 8
A12: Encounters | B12: =INDEX($I12:$M12,MATCH($B$4,$I$6:$M$6,0)) -> 20 | C12: 0 | D12: =B12-C12 -> 20 | E12: =IF(B12=0,IF(C12>0,"OVER — cut","none this milestone"),IF(D12<0,"OVER — stop & playtest",IF(D12=0,"AT CAP",D12&" left"))) -> 20 left | H12: Encounters | I12: 20 | J12: 35 | K12: 60 | L12: 250 | M12: 250
A13: Radio stations | B13: =INDEX($I13:$M13,MATCH($B$4,$I$6:$M$6,0)) -> 0 | C13: 0 | D13: =B13-C13 -> 0 | E13: =IF(B13=0,IF(C13>0,"OVER — cut","none this milestone"),IF(D13<0,"OVER — stop & playtest",IF(D13=0,"AT CAP",D13&" left"))) -> none this milestone | H13: Radio stations | I13: 0 | J13: 0 | K13: 2 | L13: 8 | M13: 8
A14: Items | B14: =INDEX($I14:$M14,MATCH($B$4,$I$6:$M$6,0)) -> 15 | C14: 0 | D14: =B14-C14 -> 15 | E14: =IF(B14=0,IF(C14>0,"OVER — cut","none this milestone"),IF(D14<0,"OVER — stop & playtest",IF(D14=0,"AT CAP",D14&" left"))) -> 15 left | H14: Items | I14: 15 | J14: 20 | K14: 30 | L14: 120 | M14: 120
A15: Weapons | B15: =INDEX($I15:$M15,MATCH($B$4,$I$6:$M$6,0)) -> 6 | C15: 0 | D15: =B15-C15 -> 6 | E15: =IF(B15=0,IF(C15>0,"OVER — cut","none this milestone"),IF(D15<0,"OVER — stop & playtest",IF(D15=0,"AT CAP",D15&" left"))) -> 6 left | H15: Weapons | I15: 6 | J15: 8 | K15: 10 | L15: 40 | M15: 40
A17: Going over a cap is NOT resolved by adding hours — cut Shoulds/Coulds or push the excess to the next milestone. Caps = one person’s review capacity. M5 = freeze (no new content).

Sheet Risk Burn-down
A1: Risk Burn-down
A2: Each PRD risk mapped to the milestone that retires it. Risk reduction is scheduled, not hoped for.
A4: Risk | B4: Impact | C4: Likelihood | D4: Retired / managed at | E4: How | F4: Status
A5: Undecided stack stalls delivery | B5: Med | C5: Med | D5: M0 | E5: Time-boxed ADR-0001; decide and move | F5: Open
A6: Systemic but not fun | B6: High | C6: Med | D6: M3 Fun Gate | E6: Prove the slice grips before any content pour | F6: Open
A7: Impressive but static world | B7: High | C7: Med | D7: M2 | E7: Off-screen evolution + director = reactive turns | F7: Open
A8: Content volume / repetition | B8: High | C8: High | D8: M4 (continuous) | E8: AI-at-volume behind review cap; recombination, Rule of Three, cooldowns; measure repeat rate | F8: Open
A9: Scope creep | B9: High | C9: High | D9: every boundary | E9: Cut filter + Won’t-now register + parking-lot change control | F9: Open
A10: Balance fragility | B10: Med | C10: Med | D10: M5 (staged passes) | E10: Director + comeback mechanics; telemetry on death timing/causes/margins | F10: Open
A11: Infection-as-identity confusing | B11: Med | C11: Med | D11: M4 | E11: Strong symptoms + optional diagnosis; comprehension-tested | F11: Open
A12: Accessibility retrofit | B12: Med | C12: Low | D12: from M1 | E12: NFR-ACC as Must from the first UI; never bolted on late | F12: Open
A13: Save-schema churn | B13: Med | C13: Med | D13: M1 onward | E13: Versioned saves + migration from the first save format | F13: Open
A14: Solo review-capacity overload | B14: High | C14: Med | D14: every milestone | E14: Content budget caps generation to what one person can gate | F14: Open

Sheet Decision Gates
A1: Decision Gates (ADRs)
A2: Open decisions tied to the milestone they must be resolved by. ADR-0001 is the one to force.
A4: ADR / decision | B4: Question | C4: Resolve by | D4: Blocks if open | E4: Decision / status
A5: ADR-0001 | B5: Engine language & runtime | C5: M0 (time-boxed) | D5: ALL code — top stall risk | E5: Open
A6: ADR-0002 | B6: Content data format (JSON/YAML/custom) | C6: M0 | D6: Content authoring tooling | E6: Open
A7: ADR-0003 | B7: Save storage & versioning | C7: M1 | D7: Save migration design | E7: Open
A8: ADR-0004 | B8: Platform ordering (native/Steam/bot) | C8: M4 | D8: Post-launch client work | E8: Open
A9: Monetization | B9: Premium / free+cosmetic / episodic | C9: M5 | D9: Launch planning | E9: Open
A10: Cross-run memory | B10: How much Living History carries between runs | C10: M4 | D10: Endings & meta-progression | E10: Open
A11: Metric thresholds | B11: Exact PRD §4 numeric targets | C11: after M2 telemetry | D11: Balance sign-off | E11: Open
A12: Licensing | B12: Proprietary / source-available / open | C12: before public beta (M4) | D12: Public distribution | E12: Open

Sheet Parking Lot
A1: Parking Lot & Won’t-Now Register
A2: New ideas land HERE, never in a live milestone. Triage only at boundaries. Won’t-now items are frozen.
A4: Idea / feature | B4: Source | C4: Serves a principle? | D4: Decision | E4: Reason | F4: Triage milestone
A5: Multiplayer / PvP | B5: PRD §6 Won’t-now | C5: No (breaks single-player focus) | D5: Won’t-now (frozen) | E5: Out of scope for v1.0; not required to prove the game | F5: —
A6: UGC / mod marketplace | B6: PRD §6 | C6: Partial (P1 content-as-data) | D6: Won’t-now (frozen) | E6: Capability yes (FR-CNT-05 Could), storefront no | F6: post-launch
A7: Cities beyond the launch city | B7: PRD §6 | C7: Yes (P3) | D7: Won’t-now (frozen) | E7: One city proves the game; more is post-launch | F7: post-launch
A8: Full faction territory wars | B8: PRD §6 | C8: Yes (P5) | D8: Won’t-now (frozen) | E8: Depth trap; factions ship shallow at v1 (FR-NPC-10 Could) | F8: post-launch
A9: Animal ecosystems | B9: PRD §6 | C9: Weak | D9: Won’t-now (frozen) | E9: No principle strongly served; recorded, not cut | F9: —
A10: Deep vehicle modification | B10: PRD §6 | C10: Weak (P4) | D10: Won’t-now (frozen) | E10: Vehicles are Could (FR-MAP-07); modification depth is not | F10: —
A11: Live-service / always-online | B11: PRD §3 non-goal | C11: No | D11: Won’t-now (frozen) | E11: Contradicts offline-capable, no-treadmill goal | F11: —
A12: (capture new ideas below — do not add to a live milestone) | D12: Parked | F12: next boundary

Sheet Fun-Gate Log
A1: Fun-Gate Log
A2: Every gate verdict. The retellable moment is the evidence. The gate governs scope.
A4: Date | B4: Stage | C4: Milestone | D4: Build / seed | E4: Retellable moment? (what) | F4: "One more day"? | G4: Decision
B5: Loop-Feel Check | C5: M1
B6: SLICE FUN GATE | C6: M3
B7: "one more day" (external) | C7: M5
